<xml xmlns="http://www.w3.org/1999/xhtml"><block type="ktaimk_tts" id="ke/Xv0t#kpoPR?{03G8q" x="388" y="77"><value name="DATA"><block type="text" id="o|8suv8@HYLcU#d.;JlW"><field name="TEXT">안녕하세요.  미세먼지를 알고 싶으시면 기가지니를 불러주세요.</field></block></value><next><block type="ktaimk_set_kws" id="bScO35U-:.*,=lMEQfgE"><field name="kws">0</field><next><block type="controls_while" id="5(,PO![2PyJMf_^v,.Q@"><value name="BOOL"><block type="logic_boolean" id="4(i]s^hoV(%DF*4Jwx!}"><field name="BOOL">TRUE</field></block></value><statement name="DO"><block type="controls_if" id="j*RmN?90@aQ`PPc4DiqK"><value name="IF0"><block type="ktaimk_detect_kws" id="H{TUU!+gkk=@.PLc/Q*#"><field name="kws">0</field></block></value><statement name="DO0"><block type="ktaimk_tts" id="`t]zy=,-ww`NKG]k;4YK"><value name="DATA"><block type="text" id="WTcck.=)b6//+{;.[E)}"><field name="TEXT">미세먼지를 알려 드리겠습니다.  원하는 지역의 공기는 어때? 라고 말씀해 보세요.</field></block></value><next><block type="variables_set" id="(v;-`wAq(A@^vXB1lE*C"><field name="VAR">인식결과</field><value name="VALUE"><block type="ktaimk_set_stt" id="FRb*pLsBp`epUf!X+b=|"></block></value><next><block type="variables_set" id="|pO#6]5%^qMvsSRo+]B~"><field name="VAR">지역</field><value name="VALUE"><block type="variables_get" id="%@ij5_1UG43:jmCaz_it"><field name="VAR">인식결과</field></block></value><next><block type="controls_if" id="@usrEKp@)[5ez3`*U@6l"><mutation else="1"></mutation><value name="IF0"><block type="logic_compare" id="k=0cZlEBb1r5Td{Tlr^L"><field name="OP">EQ</field><value name="A"><block type="variables_get" id="9qo+]Am]%S9gn;/KOHB6"><field name="VAR">지역</field></block></value><value name="B"><block type="logic_null" id=":;h7k)}`.=hhmGfrl#WB"></block></value></block></value><statement name="DO0"><block type="variables_set" id="?0KR5t}J+[I3KIo3~jW3"><field name="VAR">지역</field><value name="VALUE"><block type="text" id="+Aqgf9.v-_M*!u5nwxNH"><field name="TEXT">서울</field></block></value></block></statement><statement name="ELSE"><block type="variables_set" id="5o4@hzM_8;k+Ym[Sk%k?"><field name="VAR">지역</field><value name="VALUE"><block type="text_getSubstring" id="zGTrnei@YC~,,{IMJDv;"><mutation at1="true" at2="true"></mutation><field name="WHERE1">FROM_START</field><field name="WHERE2">FROM_START</field><value name="STRING"><block type="variables_get" id="EYiNE0z+bAR(q|Xhr{bE"><field name="VAR">지역</field></block></value><value name="AT1"><block type="math_number" id="|uh-Ar]pe0J1j_(JOtY_"><field name="NUM">1</field></block></value><value name="AT2"><block type="math_number" id="7)@*#tb?`4H.#H4V%`m:"><field name="NUM">2</field></block></value></block></value></block></statement><next><block type="variables_set" id="{_Kp8]|^!Mh%tx}ZgOMz"><field name="VAR">미세먼지</field><value name="VALUE"><block type="ktaimk_api_get_pm10" id="s7Q-8IhdlysfZ9Y.Oe8y"><value name="sido"><block type="variables_get" id="cCiFbyJQmU.YR`fh+j!`"><field name="VAR">지역</field></block></value></block></value><next><block type="variables_set" id="xd[xi1zBMUFEQg`:sBFL"><field name="VAR">초미세먼지</field><value name="VALUE"><block type="ktaimk_api_get_pm25" id="3vRp^{?o9e*?SO*0l;9C"><value name="sido"><block type="variables_get" id="1;};CxF84yFj6RKyMwCK"><field name="VAR">지역</field></block></value></block></value><next><block type="ktaimk_tts" id="[.P#fimjr0.hNF/2g?:P"><value name="DATA"><block type="variables_get" id="`TT)~AsKEN[JKwKtRvGt"><field name="VAR">지역</field></block></value><next><block type="ktaimk_tts" id="hWI~-Fc-qPC]@u-7QYE5"><value name="DATA"><block type="text" id="hU]{G/vC0-RQ|kzsi_ul"><field name="TEXT">의 현재 미세먼지는 초미세먼지</field></block></value><next><block type="ktaimk_tts" id="f!-+qL2tIW?il.bTVt!F"><value name="DATA"><block type="variables_get" id="Q3,[ooSe|bMUzl65JJUA"><field name="VAR">초미세먼지</field></block></value><next><block type="ktaimk_tts" id="wiboMd{uyHTu@7r7km2d"><value name="DATA"><block type="text" id="2RU*yKjBO{+?*x`7C4(h"><field name="TEXT">마이크로그램 이며 미세먼지</field></block></value><next><block type="ktaimk_tts" id="azUGUnOjJhC,iN2J33u("><value name="DATA"><block type="variables_get" id="x%s~wqb:rNYc~Yp|Y(Gm"><field name="VAR">미세먼지</field></block></value><next><block type="ktaimk_tts" id="3w=p-!s/J{@oSr}m6m_7"><value name="DATA"><block type="text" id="GWv|]DA[,;2V80m,^diw"><field name="TEXT">마이크로그램 으로</field></block></value><next><block type="controls_if" id="rgU+|IGWrJ6=Ua@EtrSA"><mutation elseif="2" else="1"></mutation><value name="IF0"><block type="logic_operation" id="uaQ[z(s@nZKOHAvXJ%f5"><field name="OP">AND</field><value name="A"><block type="logic_compare" id="(xqgeUT.4r[nsa+F@aJ@"><field name="OP">LT</field><value name="A"><block type="math_number" id="t6BA:u32?69mRPL1ZNdI"><field name="NUM">0</field></block></value><value name="B"><block type="variables_get" id="N9vF:SaGw%`Y+xRAfnS{"><field name="VAR">미세먼지</field></block></value></block></value><value name="B"><block type="logic_compare" id="5yC%-h`+U7rmey+AYZ5%"><field name="OP">GTE</field><value name="A"><block type="math_number" id="8oIsw4?;Mipz|W@yA]n*"><field name="NUM">30</field></block></value><value name="B"><block type="variables_get" id="yze0,sOEObuFdZpUz-w*"><field name="VAR">미세먼지</field></block></value></block></value></block></value><statement name="DO0"><block type="ktaimk_tts" id="je^#A[Xn=@e@p%6xdR/,"><value name="DATA"><block type="text" id="naP[rNs(9)Rjz#3amYHW"><field name="TEXT">오늘의 공기는 오늘 완전 좋아요. </field></block></value></block></statement><value name="IF1"><block type="logic_operation" id="Kzgwc87}RG@HiTgkE%=]"><field name="OP">AND</field><value name="A"><block type="logic_compare" id="N-Ot+B.``J-2ty%o(Z6z"><field name="OP">LT</field><value name="A"><block type="math_number" id="pNT)01X;;0#Vx^CUWr-`"><field name="NUM">30</field></block></value><value name="B"><block type="variables_get" id="`+5fWvua@SL5jDv,i!zu"><field name="VAR">미세먼지</field></block></value></block></value><value name="B"><block type="logic_compare" id="gQKS5Pp2U+sao]%g8-e}"><field name="OP">GTE</field><value name="A"><block type="math_number" id="zh53~2iHY8Lk?IwXj|4@"><field name="NUM">80</field></block></value><value name="B"><block type="variables_get" id="2{zvXp9Idt~=ENwP%x]F"><field name="VAR">미세먼지</field></block></value></block></value></block></value><statement name="DO1"><block type="ktaimk_tts" id="0c6ME=*H9eK^%3wdXS=^"><value name="DATA"><block type="text" id="zZjHT9InzpUa-~PGARZ}"><field name="TEXT">오늘의  공기는 보통이에요</field></block></value></block></statement><value name="IF2"><block type="logic_operation" id="BaWz]H{XvdD1^qT_!C~n"><field name="OP">AND</field><value name="A"><block type="logic_compare" id="*8m44.mD%XbxPb*;2;P5"><field name="OP">LT</field><value name="A"><block type="math_number" id="KyqnpZQ608-:S]A^jHZ["><field name="NUM">80</field></block></value><value name="B"><block type="variables_get" id="Faa5.LRhr}9|F}R]}FfG"><field name="VAR">미세먼지</field></block></value></block></value><value name="B"><block type="logic_compare" id="#dI#/9rbCWmV2HX`mM|x"><field name="OP">GTE</field><value name="A"><block type="math_number" id="JB!SM,IJ)8fuuZl5=Z`b"><field name="NUM">200</field></block></value><value name="B"><block type="variables_get" id="J,Kn(UbPg46lFF@87W0!"><field name="VAR">미세먼지</field></block></value></block></value></block></value><statement name="DO2"><block type="ktaimk_tts" id="u)]d*13jTKGlWwmiaYD."><value name="DATA"><block type="text" id="EYIgYeTO=Tt|z`L!*!zz"><field name="TEXT">오늘의  공기는 나쁨 이에요. 가능하면 외부 활동을 자제해 주세요.</field></block></value></block></statement><statement name="ELSE"><block type="ktaimk_tts" id="`u2^YT-!^@[RuH:ll{m7"><value name="DATA"><block type="text" id="GlE-la!0aOi]YslgA?5x"><field name="TEXT">잘 못들었습니다.</field></block></value></block></statement><next><block type="ktaimk_set_kws" id="5]P1uwGju|m|j5f#jzaL"><field name="kws">0</field></block></next></block></next></block></next></block></next></block></next></block></next></block></next></block></next></block></next></block></next></block></next></block></next></block></next></block></statement></block></statement></block></next></block></next></block></xml>